<?xml version="1.0" encoding="UTF-8"?>

<!-- generated on 22/12/2020 7:12:58 μμ by Eclipse SUMO GUI Version 98e945f8d5
<configuration xmlns:xsi="http://www.w3.org/2001/XMLSchema-instance" xsi:noNamespaceSchemaLocation="http://sumo.dlr.de/xsd/sumoConfiguration.xsd">

    <input>
        <net-file value="C:\Users\dtrou\source\repos\sumo_lanefreeplugin\lane_free_scenarios\ring_road_single_edge\ring.net.xml"/>
        <route-files value="C:\Users\dtrou\source\repos\sumo_lanefreeplugin\lane_free_scenarios\ring_road_single_edge\ring.rou.xml"/>
    </input>

    <output>
        <netstate-dump value="C:\Users\dtrou\source\repos\sumo_lanefreeplugin\lane_free_scenarios\ring_road_single_edge\statistics.xml"/>
    </output>

    <time>
        <step-length value="0.25"/>
    </time>

    <processing>
        <step-method.ballistic value="true"/>
        <collision.action value="none"/>
    </processing>

    <gui_only>
        <gui-settings-file value="C:\Users\dtrou\source\repos\sumo_lanefreeplugin\lane_free_scenarios\ring_road_single_edge\gui-settings.cfg"/>
        <tracker-interval value="0.25"/>
    </gui_only>

</configuration>
-->

<netstate xmlns:xsi="http://www.w3.org/2001/XMLSchema-instance" xsi:noNamespaceSchemaLocation="http://sumo.dlr.de/xsd/netstate_file.xsd">
    <timestep time="0.00">
        <edge id="road_stretch">
            <lane id="road_stretch_0">
                <vehicle id="lane_free_car_plugin_3" pos="6.70" speed="5.00"/>
                <vehicle id="lane_free_car_plugin_2" pos="6.70" speed="5.00"/>
                <vehicle id="lane_free_car_plugin_1" pos="6.70" speed="5.00"/>
                <vehicle id="lane_free_car_plugin_6" pos="11.70" speed="10.00"/>
                <vehicle id="lane_free_car_plugin_5" pos="11.70" speed="10.00"/>
                <vehicle id="lane_free_car_plugin_4" pos="11.70" speed="10.00"/>
                <vehicle id="lane_free_car_plugin_9" pos="16.70" speed="15.00"/>
                <vehicle id="lane_free_car_plugin_8" pos="16.70" speed="15.00"/>
                <vehicle id="lane_free_car_plugin_7" pos="16.70" speed="15.00"/>
                <vehicle id="lane_free_car_plugin_12" pos="21.70" speed="20.00"/>
                <vehicle id="lane_free_car_plugin_11" pos="21.70" speed="20.00"/>
                <vehicle id="lane_free_car_plugin_10" pos="21.70" speed="20.00"/>
                <vehicle id="lane_free_car_plugin_15" pos="26.70" speed="25.00"/>
                <vehicle id="lane_free_car_plugin_14" pos="26.70" speed="25.00"/>
                <vehicle id="lane_free_car_plugin_13" pos="26.70" speed="25.00"/>
                <vehicle id="lane_free_car_plugin_18" pos="31.70" speed="30.00"/>
                <vehicle id="lane_free_car_plugin_17" pos="31.70" speed="30.00"/>
                <vehicle id="lane_free_car_plugin_16" pos="31.70" speed="30.00"/>
                <vehicle id="lane_free_car_plugin_20" pos="36.70" speed="35.00"/>
                <vehicle id="lane_free_car_plugin_19" pos="36.70" speed="35.00"/>
            </lane>
        </edge>
    </timestep>
    <timestep time="0.25">
        <edge id="road_stretch">
            <lane id="road_stretch_0">
                <vehicle id="lane_free_car_plugin_3" pos="7.98" speed="5.25"/>
                <vehicle id="lane_free_car_plugin_2" pos="7.98" speed="5.25"/>
                <vehicle id="lane_free_car_plugin_1" pos="7.98" speed="5.25"/>
                <vehicle id="lane_free_car_plugin_6" pos="14.23" speed="10.25"/>
                <vehicle id="lane_free_car_plugin_5" pos="14.23" speed="10.25"/>
                <vehicle id="lane_free_car_plugin_4" pos="14.23" speed="10.25"/>
                <vehicle id="lane_free_car_plugin_9" pos="20.48" speed="15.25"/>
                <vehicle id="lane_free_car_plugin_8" pos="20.48" speed="15.25"/>
                <vehicle id="lane_free_car_plugin_7" pos="20.48" speed="15.25"/>
                <vehicle id="lane_free_car_plugin_12" pos="26.73" speed="20.25"/>
                <vehicle id="lane_free_car_plugin_11" pos="26.73" speed="20.25"/>
                <vehicle id="lane_free_car_plugin_10" pos="26.73" speed="20.25"/>
                <vehicle id="lane_free_car_plugin_15" pos="32.98" speed="25.25"/>
                <vehicle id="lane_free_car_plugin_14" pos="32.98" speed="25.25"/>
                <vehicle id="lane_free_car_plugin_13" pos="32.98" speed="25.25"/>
                <vehicle id="lane_free_car_plugin_18" pos="39.17" speed="29.79"/>
                <vehicle id="lane_free_car_plugin_17" pos="39.17" speed="29.75"/>
                <vehicle id="lane_free_car_plugin_16" pos="39.17" speed="29.75"/>
                <vehicle id="lane_free_car_plugin_20" pos="45.42" speed="34.75"/>
                <vehicle id="lane_free_car_plugin_19" pos="45.42" speed="34.75"/>
            </lane>
        </edge>
    </timestep>
    <timestep time="0.50">
        <edge id="road_stretch">
            <lane id="road_stretch_0">
                <vehicle id="lane_free_car_plugin_3" pos="9.32" speed="5.50"/>
                <vehicle id="lane_free_car_plugin_2" pos="9.32" speed="5.50"/>
                <vehicle id="lane_free_car_plugin_1" pos="9.32" speed="5.50"/>
                <vehicle id="lane_free_car_plugin_6" pos="16.82" speed="10.50"/>
                <vehicle id="lane_free_car_plugin_5" pos="16.82" speed="10.50"/>
                <vehicle id="lane_free_car_plugin_4" pos="16.82" speed="10.50"/>
                <vehicle id="lane_free_car_plugin_9" pos="24.32" speed="15.50"/>
                <vehicle id="lane_free_car_plugin_8" pos="24.32" speed="15.50"/>
                <vehicle id="lane_free_car_plugin_7" pos="24.32" speed="15.50"/>
                <vehicle id="lane_free_car_plugin_12" pos="31.82" speed="20.50"/>
                <vehicle id="lane_free_car_plugin_11" pos="31.82" speed="20.50"/>
                <vehicle id="lane_free_car_plugin_10" pos="31.82" speed="20.50"/>
                <vehicle id="lane_free_car_plugin_15" pos="39.33" speed="25.50"/>
                <vehicle id="lane_free_car_plugin_14" pos="39.33" speed="25.50"/>
                <vehicle id="lane_free_car_plugin_13" pos="39.32" speed="25.50"/>
                <vehicle id="lane_free_car_plugin_18" pos="46.60" speed="29.61"/>
                <vehicle id="lane_free_car_plugin_17" pos="46.58" speed="29.50"/>
                <vehicle id="lane_free_car_plugin_16" pos="46.58" speed="29.50"/>
                <vehicle id="lane_free_car_plugin_20" pos="54.08" speed="34.50"/>
                <vehicle id="lane_free_car_plugin_19" pos="54.08" speed="34.50"/>
            </lane>
        </edge>
    </timestep>
    <timestep time="0.75">
        <edge id="road_stretch">
            <lane id="road_stretch_0">
                <vehicle id="lane_free_car_plugin_3" pos="10.73" speed="5.75"/>
                <vehicle id="lane_free_car_plugin_2" pos="10.73" speed="5.75"/>
                <vehicle id="lane_free_car_plugin_1" pos="10.73" speed="5.75"/>
                <vehicle id="lane_free_car_plugin_6" pos="19.48" speed="10.75"/>
                <vehicle id="lane_free_car_plugin_5" pos="19.48" speed="10.75"/>
                <vehicle id="lane_free_car_plugin_4" pos="19.48" speed="10.75"/>
                <vehicle id="lane_free_car_plugin_9" pos="28.23" speed="15.75"/>
                <vehicle id="lane_free_car_plugin_8" pos="28.23" speed="15.75"/>
                <vehicle id="lane_free_car_plugin_7" pos="28.23" speed="15.75"/>
                <vehicle id="lane_free_car_plugin_12" pos="36.98" speed="20.75"/>
                <vehicle id="lane_free_car_plugin_11" pos="36.98" speed="20.75"/>
                <vehicle id="lane_free_car_plugin_10" pos="36.98" speed="20.75"/>
                <vehicle id="lane_free_car_plugin_15" pos="45.73" speed="25.75"/>
                <vehicle id="lane_free_car_plugin_14" pos="45.73" speed="25.75"/>
                <vehicle id="lane_free_car_plugin_13" pos="45.73" speed="25.75"/>
                <vehicle id="lane_free_car_plugin_18" pos="53.98" speed="29.45"/>
                <vehicle id="lane_free_car_plugin_17" pos="53.92" speed="29.25"/>
                <vehicle id="lane_free_car_plugin_16" pos="53.92" speed="29.25"/>
                <vehicle id="lane_free_car_plugin_20" pos="62.67" speed="34.25"/>
                <vehicle id="lane_free_car_plugin_19" pos="62.67" speed="34.25"/>
            </lane>
        </edge>
    </timestep>
    <timestep time="1.00">
        <edge id="road_stretch">
            <lane id="road_stretch_0">
                <vehicle id="lane_free_car_plugin_3" pos="12.20" speed="6.00"/>
                <vehicle id="lane_free_car_plugin_2" pos="12.20" speed="6.00"/>
                <vehicle id="lane_free_car_plugin_1" pos="12.20" speed="6.00"/>
                <vehicle id="lane_free_car_plugin_6" pos="22.20" speed="11.00"/>
                <vehicle id="lane_free_car_plugin_5" pos="22.20" speed="11.00"/>
                <vehicle id="lane_free_car_plugin_4" pos="22.20" speed="11.00"/>
                <vehicle id="lane_free_car_plugin_9" pos="32.20" speed="16.00"/>
                <vehicle id="lane_free_car_plugin_8" pos="32.20" speed="16.00"/>
                <vehicle id="lane_free_car_plugin_7" pos="32.20" speed="16.00"/>
                <vehicle id="lane_free_car_plugin_12" pos="42.20" speed="21.00"/>
                <vehicle id="lane_free_car_plugin_11" pos="42.20" speed="21.00"/>
                <vehicle id="lane_free_car_plugin_10" pos="42.20" speed="21.00"/>
                <vehicle id="lane_free_car_plugin_15" pos="52.20" speed="26.00"/>
                <vehicle id="lane_free_car_plugin_14" pos="52.20" speed="26.00"/>
                <vehicle id="lane_free_car_plugin_13" pos="52.20" speed="26.00"/>
                <vehicle id="lane_free_car_plugin_18" pos="61.33" speed="29.33"/>
                <vehicle id="lane_free_car_plugin_17" pos="61.20" speed="29.00"/>
                <vehicle id="lane_free_car_plugin_16" pos="61.20" speed="29.00"/>
                <vehicle id="lane_free_car_plugin_20" pos="71.20" speed="34.00"/>
                <vehicle id="lane_free_car_plugin_19" pos="71.20" speed="34.00"/>
            </lane>
        </edge>
    </timestep>
    <timestep time="1.25">
        <edge id="road_stretch">
            <lane id="road_stretch_0">
                <vehicle id="lane_free_car_plugin_3" pos="13.73" speed="6.25"/>
                <vehicle id="lane_free_car_plugin_2" pos="13.73" speed="6.25"/>
                <vehicle id="lane_free_car_plugin_1" pos="13.73" speed="6.25"/>
                <vehicle id="lane_free_car_plugin_6" pos="24.98" speed="11.25"/>
                <vehicle id="lane_free_car_plugin_5" pos="24.98" speed="11.25"/>
                <vehicle id="lane_free_car_plugin_4" pos="24.98" speed="11.25"/>
                <vehicle id="lane_free_car_plugin_9" pos="36.23" speed="16.25"/>
                <vehicle id="lane_free_car_plugin_8" pos="36.23" speed="16.25"/>
                <vehicle id="lane_free_car_plugin_7" pos="36.23" speed="16.25"/>
                <vehicle id="lane_free_car_plugin_12" pos="47.48" speed="21.25"/>
                <vehicle id="lane_free_car_plugin_11" pos="47.48" speed="21.25"/>
                <vehicle id="lane_free_car_plugin_10" pos="47.48" speed="21.25"/>
                <vehicle id="lane_free_car_plugin_15" pos="58.73" speed="26.25"/>
                <vehicle id="lane_free_car_plugin_14" pos="58.73" speed="26.25"/>
                <vehicle id="lane_free_car_plugin_13" pos="58.73" speed="26.25"/>
                <vehicle id="lane_free_car_plugin_18" pos="68.65" speed="29.24"/>
                <vehicle id="lane_free_car_plugin_17" pos="68.42" speed="28.75"/>
                <vehicle id="lane_free_car_plugin_16" pos="68.42" speed="28.75"/>
                <vehicle id="lane_free_car_plugin_20" pos="79.67" speed="33.75"/>
                <vehicle id="lane_free_car_plugin_19" pos="79.67" speed="33.75"/>
            </lane>
        </edge>
    </timestep>
    <timestep time="1.50">
        <edge id="road_stretch">
            <lane id="road_stretch_0">
                <vehicle id="lane_free_car_plugin_3" pos="15.32" speed="6.50"/>
                <vehicle id="lane_free_car_plugin_2" pos="15.32" speed="6.50"/>
                <vehicle id="lane_free_car_plugin_1" pos="15.32" speed="6.50"/>
                <vehicle id="lane_free_car_plugin_6" pos="27.82" speed="11.50"/>
                <vehicle id="lane_free_car_plugin_5" pos="27.82" speed="11.50"/>
                <vehicle id="lane_free_car_plugin_4" pos="27.82" speed="11.50"/>
                <vehicle id="lane_free_car_plugin_9" pos="40.33" speed="16.50"/>
                <vehicle id="lane_free_car_plugin_8" pos="40.33" speed="16.50"/>
                <vehicle id="lane_free_car_plugin_7" pos="40.33" speed="16.50"/>
                <vehicle id="lane_free_car_plugin_12" pos="52.83" speed="21.50"/>
                <vehicle id="lane_free_car_plugin_11" pos="52.83" speed="21.50"/>
                <vehicle id="lane_free_car_plugin_10" pos="52.83" speed="21.50"/>
                <vehicle id="lane_free_car_plugin_15" pos="65.33" speed="26.50"/>
                <vehicle id="lane_free_car_plugin_14" pos="65.33" speed="26.50"/>
                <vehicle id="lane_free_car_plugin_13" pos="65.32" speed="26.50"/>
                <vehicle id="lane_free_car_plugin_18" pos="75.95" speed="29.18"/>
                <vehicle id="lane_free_car_plugin_17" pos="75.58" speed="28.50"/>
                <vehicle id="lane_free_car_plugin_16" pos="75.58" speed="28.50"/>
                <vehicle id="lane_free_car_plugin_20" pos="88.08" speed="33.50"/>
                <vehicle id="lane_free_car_plugin_19" pos="88.08" speed="33.50"/>
            </lane>
        </edge>
    </timestep>
    <timestep time="1.75">
        <edge id="road_stretch">
            <lane id="road_stretch_0">
                <vehicle id="lane_free_car_plugin_3" pos="16.98" speed="6.75"/>
                <vehicle id="lane_free_car_plugin_2" pos="16.98" speed="6.75"/>
                <vehicle id="lane_free_car_plugin_1" pos="16.98" speed="6.75"/>
                <vehicle id="lane_free_car_plugin_6" pos="30.73" speed="11.75"/>
                <vehicle id="lane_free_car_plugin_5" pos="30.73" speed="11.75"/>
                <vehicle id="lane_free_car_plugin_4" pos="30.73" speed="11.75"/>
                <vehicle id="lane_free_car_plugin_9" pos="44.48" speed="16.75"/>
                <vehicle id="lane_free_car_plugin_8" pos="44.48" speed="16.75"/>
                <vehicle id="lane_free_car_plugin_7" pos="44.48" speed="16.75"/>
                <vehicle id="lane_free_car_plugin_12" pos="58.23" speed="21.75"/>
                <vehicle id="lane_free_car_plugin_11" pos="58.23" speed="21.75"/>
                <vehicle id="lane_free_car_plugin_10" pos="58.23" speed="21.75"/>
                <vehicle id="lane_free_car_plugin_15" pos="71.98" speed="26.75"/>
                <vehicle id="lane_free_car_plugin_14" pos="71.98" speed="26.75"/>
                <vehicle id="lane_free_car_plugin_13" pos="71.98" speed="26.75"/>
                <vehicle id="lane_free_car_plugin_18" pos="83.24" speed="29.13"/>
                <vehicle id="lane_free_car_plugin_17" pos="82.67" speed="28.26"/>
                <vehicle id="lane_free_car_plugin_16" pos="82.67" speed="28.25"/>
                <vehicle id="lane_free_car_plugin_20" pos="96.42" speed="33.25"/>
                <vehicle id="lane_free_car_plugin_19" pos="96.42" speed="33.25"/>
            </lane>
        </edge>
    </timestep>
    <timestep time="2.00">
        <edge id="road_stretch">
            <lane id="road_stretch_0">
                <vehicle id="lane_free_car_plugin_3" pos="18.70" speed="7.00"/>
                <vehicle id="lane_free_car_plugin_2" pos="18.70" speed="7.00"/>
                <vehicle id="lane_free_car_plugin_1" pos="18.70" speed="7.00"/>
                <vehicle id="lane_free_car_plugin_6" pos="33.70" speed="12.00"/>
                <vehicle id="lane_free_car_plugin_5" pos="33.70" speed="12.00"/>
                <vehicle id="lane_free_car_plugin_4" pos="33.70" speed="12.00"/>
                <vehicle id="lane_free_car_plugin_9" pos="48.70" speed="17.00"/>
                <vehicle id="lane_free_car_plugin_8" pos="48.70" speed="17.00"/>
                <vehicle id="lane_free_car_plugin_7" pos="48.70" speed="17.00"/>
                <vehicle id="lane_free_car_plugin_12" pos="63.70" speed="22.00"/>
                <vehicle id="lane_free_car_plugin_11" pos="63.70" speed="22.00"/>
                <vehicle id="lane_free_car_plugin_10" pos="63.70" speed="22.00"/>
                <vehicle id="lane_free_car_plugin_15" pos="78.70" speed="27.00"/>
                <vehicle id="lane_free_car_plugin_14" pos="78.70" speed="27.00"/>
                <vehicle id="lane_free_car_plugin_13" pos="78.70" speed="27.00"/>
                <vehicle id="lane_free_car_plugin_18" pos="90.52" speed="29.09"/>
                <vehicle id="lane_free_car_plugin_17" pos="89.71" speed="28.03"/>
                <vehicle id="lane_free_car_plugin_16" pos="89.70" speed="28.00"/>
                <vehicle id="lane_free_car_plugin_20" pos="104.70" speed="33.00"/>
                <vehicle id="lane_free_car_plugin_19" pos="104.70" speed="33.00"/>
            </lane>
        </edge>
    </timestep>
    <timestep time="2.25">
        <edge id="road_stretch">
            <lane id="road_stretch_0">
                <vehicle id="lane_free_car_plugin_3" pos="20.48" speed="7.25"/>
                <vehicle id="lane_free_car_plugin_2" pos="20.48" speed="7.25"/>
                <vehicle id="lane_free_car_plugin_1" pos="20.48" speed="7.25"/>
                <vehicle id="lane_free_car_plugin_6" pos="36.73" speed="12.25"/>
                <vehicle id="lane_free_car_plugin_5" pos="36.73" speed="12.25"/>
                <vehicle id="lane_free_car_plugin_4" pos="36.73" speed="12.25"/>
                <vehicle id="lane_free_car_plugin_9" pos="52.98" speed="17.25"/>
                <vehicle id="lane_free_car_plugin_8" pos="52.98" speed="17.25"/>
                <vehicle id="lane_free_car_plugin_7" pos="52.98" speed="17.25"/>
                <vehicle id="lane_free_car_plugin_12" pos="69.23" speed="22.25"/>
                <vehicle id="lane_free_car_plugin_11" pos="69.23" speed="22.25"/>
                <vehicle id="lane_free_car_plugin_10" pos="69.23" speed="22.25"/>
                <vehicle id="lane_free_car_plugin_15" pos="85.48" speed="27.25"/>
                <vehicle id="lane_free_car_plugin_14" pos="85.48" speed="27.25"/>
                <vehicle id="lane_free_car_plugin_13" pos="85.48" speed="27.25"/>
                <vehicle id="lane_free_car_plugin_18" pos="97.79" speed="29.07"/>
                <vehicle id="lane_free_car_plugin_17" pos="96.69" speed="27.82"/>
                <vehicle id="lane_free_car_plugin_16" pos="96.67" speed="27.75"/>
                <vehicle id="lane_free_car_plugin_20" pos="112.92" speed="32.75"/>
                <vehicle id="lane_free_car_plugin_19" pos="112.92" speed="32.75"/>
            </lane>
        </edge>
    </timestep>
    <timestep time="2.50">
        <edge id="road_stretch">
            <lane id="road_stretch_0">
                <vehicle id="lane_free_car_plugin_3" pos="22.32" speed="7.50"/>
                <vehicle id="lane_free_car_plugin_2" pos="22.32" speed="7.50"/>
                <vehicle id="lane_free_car_plugin_1" pos="22.32" speed="7.50"/>
                <vehicle id="lane_free_car_plugin_6" pos="39.83" speed="12.50"/>
                <vehicle id="lane_free_car_plugin_5" pos="39.83" speed="12.50"/>
                <vehicle id="lane_free_car_plugin_4" pos="39.83" speed="12.50"/>
                <vehicle id="lane_free_car_plugin_9" pos="57.33" speed="17.50"/>
                <vehicle id="lane_free_car_plugin_8" pos="57.33" speed="17.50"/>
                <vehicle id="lane_free_car_plugin_7" pos="57.33" speed="17.50"/>
                <vehicle id="lane_free_car_plugin_12" pos="74.83" speed="22.50"/>
                <vehicle id="lane_free_car_plugin_11" pos="74.83" speed="22.50"/>
                <vehicle id="lane_free_car_plugin_10" pos="74.83" speed="22.50"/>
                <vehicle id="lane_free_car_plugin_15" pos="92.33" speed="27.50"/>
                <vehicle id="lane_free_car_plugin_14" pos="92.33" speed="27.50"/>
                <vehicle id="lane_free_car_plugin_13" pos="92.32" speed="27.50"/>
                <vehicle id="lane_free_car_plugin_18" pos="105.05" speed="29.05"/>
                <vehicle id="lane_free_car_plugin_17" pos="103.62" speed="27.63"/>
                <vehicle id="lane_free_car_plugin_16" pos="103.58" speed="27.50"/>
                <vehicle id="lane_free_car_plugin_20" pos="121.08" speed="32.50"/>
                <vehicle id="lane_free_car_plugin_19" pos="121.08" speed="32.50"/>
            </lane>
        </edge>
    </timestep>
    <timestep time="2.75">
        <edge id="road_stretch">
            <lane id="road_stretch_0">
                <vehicle id="lane_free_car_plugin_3" pos="24.23" speed="7.75"/>
                <vehicle id="lane_free_car_plugin_2" pos="24.23" speed="7.75"/>
                <vehicle id="lane_free_car_plugin_1" pos="24.23" speed="7.75"/>
                <vehicle id="lane_free_car_plugin_6" pos="42.98" speed="12.75"/>
                <vehicle id="lane_free_car_plugin_5" pos="42.98" speed="12.75"/>
                <vehicle id="lane_free_car_plugin_4" pos="42.98" speed="12.75"/>
                <vehicle id="lane_free_car_plugin_9" pos="61.73" speed="17.75"/>
                <vehicle id="lane_free_car_plugin_8" pos="61.73" speed="17.75"/>
                <vehicle id="lane_free_car_plugin_7" pos="61.73" speed="17.75"/>
                <vehicle id="lane_free_car_plugin_12" pos="80.48" speed="22.75"/>
                <vehicle id="lane_free_car_plugin_11" pos="80.48" speed="22.75"/>
                <vehicle id="lane_free_car_plugin_10" pos="80.48" speed="22.75"/>
                <vehicle id="lane_free_car_plugin_15" pos="99.23" speed="27.75"/>
                <vehicle id="lane_free_car_plugin_14" pos="99.23" speed="27.75"/>
                <vehicle id="lane_free_car_plugin_13" pos="99.23" speed="27.74"/>
                <vehicle id="lane_free_car_plugin_18" pos="112.31" speed="29.03"/>
                <vehicle id="lane_free_car_plugin_17" pos="110.51" speed="27.47"/>
                <vehicle id="lane_free_car_plugin_16" pos="110.42" speed="27.26"/>
                <vehicle id="lane_free_car_plugin_20" pos="129.17" speed="32.25"/>
                <vehicle id="lane_free_car_plugin_19" pos="129.17" speed="32.25"/>
            </lane>
        </edge>
    </timestep>
    <timestep time="3.00">
        <edge id="road_stretch">
            <lane id="road_stretch_0">
                <vehicle id="lane_free_car_plugin_3" pos="26.20" speed="8.00"/>
                <vehicle id="lane_free_car_plugin_2" pos="26.20" speed="8.00"/>
                <vehicle id="lane_free_car_plugin_1" pos="26.20" speed="8.00"/>
                <vehicle id="lane_free_car_plugin_6" pos="46.20" speed="13.00"/>
                <vehicle id="lane_free_car_plugin_5" pos="46.20" speed="13.00"/>
                <vehicle id="lane_free_car_plugin_4" pos="46.20" speed="13.00"/>
                <vehicle id="lane_free_car_plugin_9" pos="66.20" speed="18.00"/>
                <vehicle id="lane_free_car_plugin_8" pos="66.20" speed="18.00"/>
                <vehicle id="lane_free_car_plugin_7" pos="66.20" speed="18.00"/>
                <vehicle id="lane_free_car_plugin_12" pos="86.20" speed="23.00"/>
                <vehicle id="lane_free_car_plugin_11" pos="86.20" speed="23.00"/>
                <vehicle id="lane_free_car_plugin_10" pos="86.20" speed="23.00"/>
                <vehicle id="lane_free_car_plugin_15" pos="106.20" speed="28.00"/>
                <vehicle id="lane_free_car_plugin_14" pos="106.20" speed="28.00"/>
                <vehicle id="lane_free_car_plugin_13" pos="106.19" speed="27.97"/>
                <vehicle id="lane_free_car_plugin_18" pos="119.57" speed="29.02"/>
                <vehicle id="lane_free_car_plugin_17" pos="117.36" speed="27.35"/>
                <vehicle id="lane_free_car_plugin_16" pos="117.21" speed="27.03"/>
                <vehicle id="lane_free_car_plugin_20" pos="137.20" speed="32.00"/>
                <vehicle id="lane_free_car_plugin_19" pos="137.20" speed="32.00"/>
            </lane>
        </edge>
    </timestep>
    <timestep time="3.25">
        <edge id="road_stretch">
            <lane id="road_stretch_0">
                <vehicle id="lane_free_car_plugin_3" pos="28.23" speed="8.25"/>
                <vehicle id="lane_free_car_plugin_2" pos="28.23" speed="8.25"/>
                <vehicle id="lane_free_car_plugin_1" pos="28.23" speed="8.25"/>
                <vehicle id="lane_free_car_plugin_6" pos="49.48" speed="13.25"/>
                <vehicle id="lane_free_car_plugin_5" pos="49.48" speed="13.25"/>
                <vehicle id="lane_free_car_plugin_4" pos="49.48" speed="13.25"/>
                <vehicle id="lane_free_car_plugin_9" pos="70.73" speed="18.25"/>
                <vehicle id="lane_free_car_plugin_8" pos="70.73" speed="18.25"/>
                <vehicle id="lane_free_car_plugin_7" pos="70.73" speed="18.25"/>
                <vehicle id="lane_free_car_plugin_12" pos="91.98" speed="23.25"/>
                <vehicle id="lane_free_car_plugin_11" pos="91.98" speed="23.25"/>
                <vehicle id="lane_free_car_plugin_10" pos="91.98" speed="23.25"/>
                <vehicle id="lane_free_car_plugin_15" pos="113.23" speed="28.25"/>
                <vehicle id="lane_free_car_plugin_14" pos="113.23" speed="28.25"/>
                <vehicle id="lane_free_car_plugin_13" pos="113.21" speed="28.18"/>
                <vehicle id="lane_free_car_plugin_18" pos="126.82" speed="29.02"/>
                <vehicle id="lane_free_car_plugin_17" pos="124.19" speed="27.25"/>
                <vehicle id="lane_free_car_plugin_16" pos="123.94" speed="26.82"/>
                <vehicle id="lane_free_car_plugin_20" pos="145.17" speed="31.75"/>
                <vehicle id="lane_free_car_plugin_19" pos="145.17" speed="31.75"/>
            </lane>
        </edge>
    </timestep>
    <timestep time="3.50">
        <edge id="road_stretch">
            <lane id="road_stretch_0">
                <vehicle id="lane_free_car_plugin_3" pos="30.32" speed="8.50"/>
                <vehicle id="lane_free_car_plugin_2" pos="30.32" speed="8.50"/>
                <vehicle id="lane_free_car_plugin_1" pos="30.32" speed="8.50"/>
                <vehicle id="lane_free_car_plugin_6" pos="52.83" speed="13.50"/>
                <vehicle id="lane_free_car_plugin_5" pos="52.83" speed="13.50"/>
                <vehicle id="lane_free_car_plugin_4" pos="52.83" speed="13.50"/>
                <vehicle id="lane_free_car_plugin_9" pos="75.33" speed="18.50"/>
                <vehicle id="lane_free_car_plugin_8" pos="75.33" speed="18.50"/>
                <vehicle id="lane_free_car_plugin_7" pos="75.33" speed="18.50"/>
                <vehicle id="lane_free_car_plugin_12" pos="97.83" speed="23.50"/>
                <vehicle id="lane_free_car_plugin_11" pos="97.83" speed="23.50"/>
                <vehicle id="lane_free_car_plugin_10" pos="97.83" speed="23.50"/>
                <vehicle id="lane_free_car_plugin_15" pos="120.33" speed="28.50"/>
                <vehicle id="lane_free_car_plugin_14" pos="120.32" speed="28.50"/>
                <vehicle id="lane_free_car_plugin_13" pos="120.28" speed="28.37"/>
                <vehicle id="lane_free_car_plugin_18" pos="134.08" speed="29.01"/>
                <vehicle id="lane_free_car_plugin_17" pos="130.99" speed="27.18"/>
                <vehicle id="lane_free_car_plugin_16" pos="130.62" speed="26.63"/>
                <vehicle id="lane_free_car_plugin_20" pos="153.08" speed="31.50"/>
                <vehicle id="lane_free_car_plugin_19" pos="153.08" speed="31.50"/>
            </lane>
        </edge>
    </timestep>
</netstate>
